paperboy/__init__.py
paperboy/__main__.py
paperboy/_version.py
paperboy/utils.py
paperboy/assets/README.md
paperboy/assets/static/css/font-awesome.min.css
paperboy/assets/static/css/login.css
paperboy/assets/static/fonts/fontawesome-webfont.woff
paperboy/assets/static/fonts/fonts.css
paperboy/assets/static/fonts/mem5YaGs126MiZpBA-UN_r8OUuhs.ttf
paperboy/assets/static/fonts/mem5YaGs126MiZpBA-UNirkOUuhs.ttf
paperboy/assets/static/fonts/mem8YaGs126MiZpBA-UFVZ0e.ttf
paperboy/assets/static/fonts/z7NFdQDnbTkabZAIOl9il_O6KJj73e7Ff0GmDuXMQg.ttf
paperboy/assets/static/fonts/z7NFdQDnbTkabZAIOl9il_O6KJj73e7Ff1GhDuXMQg.ttf
paperboy/assets/static/img/paperboy.jpg
paperboy/assets/static/js/bundle.js
paperboy/assets/static/js/perspective.worker.async.js
paperboy/assets/static/js/perspective.worker.async.js.map
paperboy/assets/static/js/psp.async.wasm
paperboy/assets/templates/404.html
paperboy/assets/templates/index.html
paperboy/assets/templates/login.html
paperboy/assets/templates/logout.html
paperboy/assets/templates/register.html
paperboy/config/__init__.py
paperboy/config/application.py
paperboy/config/base.py
paperboy/config/forms.py
paperboy/config/job.py
paperboy/config/notebook.py
paperboy/config/output.py
paperboy/config/report.py
paperboy/config/scheduler.py
paperboy/config/storage.py
paperboy/config/user.py
paperboy/middleware/__init__.py
paperboy/middleware/auth_required.py
paperboy/middleware/cors.py
paperboy/middleware/load_user.py
paperboy/middleware/multipart.py
paperboy/middleware/none.py
paperboy/middleware/sqla.py
paperboy/output/__init__.py
paperboy/output/_email.py
paperboy/output/base.py
paperboy/output/local.py
paperboy/output/sqla.py
paperboy/resources/__init__.py
paperboy/resources/autocomplete.py
paperboy/resources/base.py
paperboy/resources/config.py
paperboy/resources/html.py
paperboy/resources/job.py
paperboy/resources/login.py
paperboy/resources/logout.py
paperboy/resources/notebook.py
paperboy/resources/register.py
paperboy/resources/report.py
jupyter_paperboy-0.1.2.dist-info/LICENSE
jupyter_paperboy-0.1.2.dist-info/METADATA
jupyter_paperboy-0.1.2.dist-info/WHEEL
jupyter_paperboy-0.1.2.dist-info/entry_points.txt
jupyter_paperboy-0.1.2.dist-info/top_level.txt
jupyter_paperboy-0.1.2.dist-info/RECORD
