Metadata-Version: 2.1
Name: jupyter-paperboy
Version: 0.1.2
Summary: Jupyter notebooks
Home-page: https://github.com/timkpaine/paperboy
Author: Tim Paine
Author-email: timothy.k.paine@gmail.com
License: BSD 3 Clause
Download-URL: https://github.com/timkpaine/paperboy/archive/v0.1.2.tar.gz
Keywords: juyter notebooks jupyterlab analytics
Platform: UNKNOWN
Classifier: Development Status :: 3 - Alpha
Classifier: Programming Language :: Python :: 2
Classifier: Programming Language :: Python :: 2.7
Classifier: Programming Language :: Python :: 3
Classifier: Programming Language :: Python :: 3.3
Classifier: Programming Language :: Python :: 3.4
Classifier: Programming Language :: Python :: 3.5
Classifier: Programming Language :: Python :: 3.6
Classifier: Programming Language :: Python :: 3.7
Requires-Dist: falcon (==1.4.1)
Requires-Dist: gunicorn (>=19.9.0)
Requires-Dist: gitpython (>=2.1.11)
Requires-Dist: Jinja2 (>=2.8.1)
Requires-Dist: nbconvert (>=5.4.0)
Requires-Dist: nbformat (>=4.4.0)
Requires-Dist: nbstripout (>=0.3.3)
Requires-Dist: papermill (>=0.16.2)
Requires-Dist: python-crontab (>=2.3.8)
Requires-Dist: PyJWT (>=1.6.4)
Requires-Dist: traitlets (>=4.3.2)
Requires-Dist: voila (>=0.0.6)
Requires-Dist: waitress
Provides-Extra: dev
Requires-Dist: falcon (==1.4.1) ; extra == 'dev'
Requires-Dist: gunicorn (>=19.9.0) ; extra == 'dev'
Requires-Dist: gitpython (>=2.1.11) ; extra == 'dev'
Requires-Dist: Jinja2 (>=2.8.1) ; extra == 'dev'
Requires-Dist: nbconvert (>=5.4.0) ; extra == 'dev'
Requires-Dist: nbformat (>=4.4.0) ; extra == 'dev'
Requires-Dist: nbstripout (>=0.3.3) ; extra == 'dev'
Requires-Dist: papermill (>=0.16.2) ; extra == 'dev'
Requires-Dist: python-crontab (>=2.3.8) ; extra == 'dev'
Requires-Dist: PyJWT (>=1.6.4) ; extra == 'dev'
Requires-Dist: traitlets (>=4.3.2) ; extra == 'dev'
Requires-Dist: voila (>=0.0.6) ; extra == 'dev'
Requires-Dist: waitress ; extra == 'dev'
Requires-Dist: pytest ; extra == 'dev'
Requires-Dist: pytest-cov ; extra == 'dev'
Requires-Dist: pytest-falcon ; extra == 'dev'
Requires-Dist: pylint ; extra == 'dev'
Requires-Dist: flake8 ; extra == 'dev'
